netflix_open_content_helper/__init__.py
netflix_open_content_helper/__main__.py
netflix_open_content_helper/cli.py
netflix_open_content_helper/models.py
netflix_open_content_helper/parser.py
netflix_open_content_helper/config/config.yaml
netflix_open_content_helper-0.2.0.dist-info/METADATA
netflix_open_content_helper-0.2.0.dist-info/WHEEL
netflix_open_content_helper-0.2.0.dist-info/entry_points.txt
netflix_open_content_helper-0.2.0.dist-info/licenses/LICENSE
netflix_open_content_helper-0.2.0.dist-info/RECORD
